[
  { "code": "sr", "name": "Serbian" },
  { "code": "hr", "name": "Croatian" },
  { "code": "bs", "name": "Bosnian" },
  { "code": "sl", "name": "Slovenian" },
  { "code": "mk", "name": "Macedonian" },
  { "code": "bg", "name": "Bulgarian" },
  { "code": "ru", "name": "Russian" },
  { "code": "uk", "name": "Ukrainian" },
  { "code": "be", "name": "Belarusian" },
  { "code": "pl", "name": "Polish" },
  { "code": "cs", "name": "Czech" },
  { "code": "sk", "name": "Slovak" },
  { "code": "hu", "name": "Hungarian" },
  { "code": "ro", "name": "Romanian" },
  { "code": "el", "name": "Greek" },
  { "code": "tr", "name": "Turkish" },
  { "code": "ar", "name": "Arabic" },
  { "code": "he", "name": "Hebrew" },
  { "code": "fa", "name": "Persian" },
  { "code": "th", "name": "Thai" },
  { "code": "vi", "name": "Vietnamese" },
  { "code": "zh", "name": "Chinese" },
  { "code": "ja", "name": "Japanese" },
  { "code": "ko", "name": "Korean" },
  { "code": "en", "name": "English" },
  { "code": "de", "name": "German" },
  { "code": "fr", "name": "French" },
  { "code": "es", "name": "Spanish" },
  { "code": "it", "name": "Italian" },
  { "code": "pt", "name": "Portuguese" },
  { "code": "nl", "name": "Dutch" },
  { "code": "sv", "name": "Swedish" },
  { "code": "no", "name": "Norwegian" },
  { "code": "da", "name": "Danish" },
  { "code": "fi", "name": "Finnish" }
]
